BrainFuck/__init__.py
BrainFuck/simple.py
theBrainFuck-0.0.3.dist-info/METADATA
theBrainFuck-0.0.3.dist-info/WHEEL
theBrainFuck-0.0.3.dist-info/top_level.txt
theBrainFuck-0.0.3.dist-info/RECORD
