Metadata-Version: 2.1
Name: theBrainFuck
Version: 0.0.3
Summary: My Own Machine Learning Packages
Home-page: UNKNOWN
Author: ZhouYihang
Author-email: chk18351887132@gmail.com
License: UNKNOWN
Platform: UNKNOWN
Classifier: Programming Language :: Python :: 3
Classifier: License :: OSI Approved :: MIT License
Classifier: Operating System :: OS Independent
Requires-Dist: scipy
Requires-Dist: numpy
Requires-Dist: pandas
Requires-Dist: matplotlib
Requires-Dist: sklearn
